galaxyxml/__init__.py
galaxyxml/tool/__init__.py
galaxyxml/tool/import_xml.py
galaxyxml/tool/parameters/__init__.py
galaxyxml-0.5.5.data/data/LICENSE.TXT
galaxyxml-0.5.5.dist-info/LICENSE.TXT
galaxyxml-0.5.5.dist-info/METADATA
galaxyxml-0.5.5.dist-info/WHEEL
galaxyxml-0.5.5.dist-info/top_level.txt
galaxyxml-0.5.5.dist-info/RECORD
