Metadata-Version: 2.1
Name: galaxyxml
Version: 0.5.5
Summary: Galaxy XML generation library
Author: Helena Rasche
Author-email: hexylena@galaxians.org
Classifier: Development Status :: 4 - Beta
Classifier: Operating System :: OS Independent
Classifier: Intended Audience :: Developers
Classifier: Environment :: Console
Classifier: License :: OSI Approved :: Apache Software License
License-File: LICENSE.TXT
Requires-Dist: galaxy-tool-util
Requires-Dist: lxml
